{"cameraMode":{"drawMode":0,"name":"Shaded","section":"Shading Mode"},"sceneLighting":false,"audioPlay":false,"sceneViewState":{"m_AlwaysRefresh":false,"showFog":true,"showSkybox":false,"showFlares":true,"showImageEffects":true,"showParticleSystems":true,"showVisualEffectGraphs":true,"m_FxEnabled":true},"in2DMode":false,"pivot":{"x":0.000012159347534179688,"y":2.9997968673706056,"z":0.499988317489624},"rotation":{"x":0.06814815104007721,"y":-0.7207430601119995,"z":0.07158796489238739,"w":0.6861248016357422},"size":6.3486528396606449,"orthographic":false}